{
	"name": "Large Slate Wall",
	"description": "Has more health and shrapnel.",
	"type": "Wall",
	"health": 1200,
	"size": 2,
	"requirements": [
		{ "item": "slate", "amount": 24 }
	],
	"category": "defense",
	"research": "6w02",
	"destroyBullet": {
		"type": "BasicBulletType",
		"instantDisappear": true,
		"hitSound": "explosion",
		"hitSoundVolume": 1,
		"damage": 40,
		"lifeTime": 1,
		"speed": 0,
		"width": 20,
		"height": 20,
		"collidesAir": false,
		"collidesGround": false,
		"collidesTiles": false,
		"shootEffect": none,
		"despawnEffect": none,
		"fragBullets": 30,
		"fragBullet": {
			"type": "BasicBulletType",
			"damage": 12,
			"lifeTime": 16,
			"speed": 6,
			"width": 3,
			"height": 12,
		}
	}
	"destroyBulletSameTeam": true
}
